{
  "project_info": {
    "project_number": "362572368899",
    "project_id": "dlinks-4725e",
    "storage_bucket": "dlinks-4725e.appspot.com"
  },
  "client": [
    {
      "client_info": {
        "mobilesdk_app_id": "1:362572368899:android:5204f5af4bbc952bba5236",
        "android_client_info": {
          "package_name": "com.example.dlinks"
        }
      },
      "oauth_client": [
        {
          "client_id": "362572368899-k54hd61qq5cjqp9qklnbg0uea59aukfk.apps.googleusercontent.com",
          "client_type": 3
        }
      ],
      "api_key": [
        {
          "current_key": "AIzaSyDFRU-iWN49xLlKgeQSYkaWSJpZZDQTW_o"
        }
      ],
      "services": {
        "appinvite_service": {
          "other_platform_oauth_client": [
            {
              "client_id": "362572368899-k54hd61qq5cjqp9qklnbg0uea59aukfk.apps.googleusercontent.com",
              "client_type": 3
            }
          ]
        }
      }
    }
  ],
  "configuration_version": "1"
}